django_mlcommenting/__init__.py
django_mlcommenting/admin.py
django_mlcommenting/apps.py
django_mlcommenting/forms.py
django_mlcommenting/models.py
django_mlcommenting/urls.py
django_mlcommenting/utils.py
django_mlcommenting/views.py
django_mlcommenting-0.1.1.dist-info/METADATA
django_mlcommenting-0.1.1.dist-info/WHEEL
django_mlcommenting-0.1.1.dist-info/top_level.txt
django_mlcommenting-0.1.1.dist-info/RECORD
