Metadata-Version: 2.1
Name: django-mlcommenting
Version: 0.1.1
Summary: Django commenting and object rating module with buildin google translation
Home-page: https://github.com/domlysi/django-mlcommenting
Author: Dominik Lysiak
Author-email: dominik.lysiak@freenet.de
License: UNKNOWN
Keywords: python django django-module
Platform: UNKNOWN
Classifier: Development Status :: 4 - Beta
Classifier: Intended Audience :: Developers
Classifier: Topic :: Software Development :: Libraries :: Python Modules
Classifier: License :: OSI Approved :: MIT License
Classifier: Programming Language :: Python :: 3
Classifier: Programming Language :: Python :: 3.5
Classifier: Programming Language :: Python :: 3.6
Classifier: Programming Language :: Python :: 3.7
Classifier: Framework :: Django :: 2.0
Classifier: Framework :: Django :: 2.1
Classifier: Framework :: Django :: 2.2
Requires-Python: !=3.0.*, !=3.1.*, !=3.2.*, !=3.3.*, !=3.4.*, <4
